config_wrapper/__init__.py
config_wrapper/config_manager.py
config_wrapper/exceptions.py
config_wrapper-0.0.12.dist-info/LICENSE
config_wrapper-0.0.12.dist-info/METADATA
config_wrapper-0.0.12.dist-info/WHEEL
config_wrapper-0.0.12.dist-info/top_level.txt
config_wrapper-0.0.12.dist-info/RECORD
