Metadata-Version: 2.1
Name: config-wrapper
Version: 0.0.12
Summary: Simple wrapper for cofigparser
Home-page: https://github.com/pzielski/config-wrapper
Author: Piotr Zielski
Author-email: zielskipiotr@gmail.com
License: UNKNOWN
Project-URL: Bug Tracker, https://github.com/pzielski/config-wrapper/issues
Platform: UNKNOWN
Classifier: Programming Language :: Python :: 3
Classifier: License :: OSI Approved :: MIT License
Classifier: Operating System :: OS Independent
Requires-Python: >=3.7
